xialib_hana/__init__.py
xialib_hana/hana_adaptor.py
xialib_hana-0.0.5.dist-info/LICENSE
xialib_hana-0.0.5.dist-info/METADATA
xialib_hana-0.0.5.dist-info/WHEEL
xialib_hana-0.0.5.dist-info/top_level.txt
xialib_hana-0.0.5.dist-info/RECORD
