Metadata-Version: 2.1
Name: xialib-hana
Version: 0.0.5
Summary: X-I-A HANA Library
Home-page: https://github.com/X-I-A/xialib-hana
Author: Soral
Author-email: soral@x-i-a.com
License: UNKNOWN
Platform: UNKNOWN
Classifier: Programming Language :: Python :: 3
Classifier: License :: OSI Approved :: GNU General Public License v3 (GPLv3)
Classifier: Operating System :: OS Independent
Requires-Python: >=3.6
Requires-Dist: xialib
Requires-Dist: hdbcli
